py_viptela/__init__.py
py_viptela/query_builder.py
py_viptela/response_parser.py
py_viptela/restclient.py
py_viptela/vmanage.py
py_viptela/api/__init__.py
py_viptela/api/backup.py
py_viptela/api/cluster.py
py_viptela/api/datacollection.py
py_viptela/api/deployment.py
py_viptela/api/locale.py
py_viptela/api/msla.py
py_viptela/api/sdavc.py
py_viptela/api/smartlicense.py
py_viptela/api/umbrella.py
py_viptela/api/workflow.py
py_viptela/api/admin/__init__.py
py_viptela/api/admin/audit.py
py_viptela/api/admin/user.py
py_viptela/api/cert/__init__.py
py_viptela/api/cert/device.py
py_viptela/api/cert/vmanage.py
py_viptela/api/colo/__init__.py
py_viptela/api/colo/chain.py
py_viptela/api/colo/cluster.py
py_viptela/api/colo/group.py
py_viptela/api/config/__init__.py
py_viptela/api/config/azure.py
py_viptela/api/config/cexp.py
py_viptela/api/config/circuits.py
py_viptela/api/config/cor.py
py_viptela/api/config/dashboard.py
py_viptela/api/config/disaster.py
py_viptela/api/config/featurecert.py
py_viptela/api/config/multicloud.py
py_viptela/api/config/networkdesign.py
py_viptela/api/config/segments.py
py_viptela/api/config/settings.py
py_viptela/api/config/sig.py
py_viptela/api/config/softwareactions.py
py_viptela/api/config/topology.py
py_viptela/api/config/assembler/__init__.py
py_viptela/api/config/assembler/security.py
py_viptela/api/config/assembler/vedge.py
py_viptela/api/config/assembler/voice.py
py_viptela/api/config/assembler/vsmart.py
py_viptela/api/config/builder/__init__.py
py_viptela/api/config/builder/definition/__init__.py
py_viptela/api/config/builder/definition/acl.py
py_viptela/api/config/builder/definition/acl6.py
py_viptela/api/config/builder/definition/amp.py
py_viptela/api/config/builder/definition/approute.py
py_viptela/api/config/builder/definition/cflowd.py
py_viptela/api/config/builder/definition/control.py
py_viptela/api/config/builder/definition/data.py
py_viptela/api/config/builder/definition/deviceacl.py
py_viptela-0.2.9.8.5.dist-info/LICENSE
py_viptela-0.2.9.8.5.dist-info/METADATA
py_viptela-0.2.9.8.5.dist-info/NOTICE
py_viptela-0.2.9.8.5.dist-info/WHEEL
py_viptela-0.2.9.8.5.dist-info/top_level.txt
py_viptela-0.2.9.8.5.dist-info/RECORD
