Metadata-Version: 2.1
Name: py-viptela
Version: 0.2.9.8.5
Summary: A Python wrapper around Cisco vManage API
Home-page: https://github.com/aatikturk/py_viptela
Author: Adem Atikturk
Author-email: aatikturk@gmail.com
License: GNU General Public License v2.0
Requires-Python: >=3
License-File: LICENSE
License-File: NOTICE
Requires-Dist: requests
